{
  "books": [
    {
      "title": "Purple Hibiscus",
      "authors": "Chimamanda Ngozi Adichie",
      "status": "completed",
      "total_pages": 307,
      "date_completed": "11 Oct 2025"
    },
    {
      "title": "Middlemarch",
      "authors": "George Eliot",
      "status": "currently_reading",
      "total_pages": 713
    },
    {
      "title": "Project Hail Mary",
      "authors": "Andy Weir",
      "status": "currently_reading",
      "total_pages": 496
    },
    {
      "title": "Salem's Lot",
      "authors": "Stephen King",
      "status": "want_to_read",
      "total_pages": 653,
      "pages_read": 5
    },
    {
      "title": "All Quiet on the Western Front",
      "authors": "Erich Maria Remarque",
      "status": "want_to_read",
      "total_pages": 296
    },
    {
      "title": "Fight Club",
      "authors": "Chuck Palahniuk",
      "status": "want_to_read",
      "total_pages": 224
    },
    {
      "title": "The Stand",
      "authors": "Stephen King",
      "status": "want_to_read",
      "total_pages": 651
    },

    {
      "title": "The Wind-Up Bird Chronicle",
      "authors": "Haruki Murakami",
      "status": "currently_reading",
      "total_pages": 609,
      "pages_read": 53
    }
  ]
}
